<?xml version="1.0" encoding="UTF-8" standalone="no"?>
<gameState>
    <entities>
        <entity type="Player">
            <x>478.0</x>
            <y>480.0</y>
        </entity>
        <entity type="NPC">
            <x>540.0</x>
            <y>480.0</y>
            <dialogue currentLine="1">
                <line>Greetings noble knight!</line>
                <line>Our town is plagued by ghouls! Would you be so kind to help us?</line>
                <line>We would be eternally grateful for your assistance!</line>
            </dialogue>
        </entity>
    </entities>
</gameState>
